cachaca/cachaca.py
cachaca-0.0.1.dist-info/METADATA
cachaca-0.0.1.dist-info/WHEEL
cachaca-0.0.1.dist-info/licenses/LICENSE
cachaca-0.0.1.dist-info/RECORD
